async_worker_flow-0.2.0.dist-info/licenses/LICENSE
asyncflow/__init__.py
asyncflow/_version.py
asyncflow/exceptions.py
asyncflow/executor.py
asyncflow/pipeline.py
asyncflow/tracker.py
asyncflow/types.py
asyncflow/utils.py
async_worker_flow-0.2.0.dist-info/METADATA
async_worker_flow-0.2.0.dist-info/WHEEL
async_worker_flow-0.2.0.dist-info/top_level.txt
async_worker_flow-0.2.0.dist-info/RECORD
