Metadata-Version: 2.4
Name: async-worker-flow
Version: 0.2.0
Summary: Async execution library with concurrent.futures-style API and advanced pipelines
Author-email: Rodolfo Nobrega <rodolfo@example.com>
License: MIT
Project-URL: Homepage, https://github.com/rodolfonobrega/async-worker-flow
Project-URL: Documentation, https://async-worker-flow.readthedocs.io
Project-URL: Repository, https://github.com/rodolfonobrega/async-worker-flow
Project-URL: Issues, https://github.com/rodolfonobrega/async-worker-flow/issues
Keywords: async,asyncio,pipeline,concurrent,futures,executor,worker-pool
Classifier: Development Status :: 4 - Beta
Classifier: Intended Audience :: Developers
Classifier: License :: OSI Approved :: MIT License
Classifier: Programming Language :: Python :: 3
Classifier: Programming Language :: Python :: 3.9
Classifier: Programming Language :: Python :: 3.10
Classifier: Programming Language :: Python :: 3.11
Classifier: Programming Language :: Python :: 3.12
Classifier: Programming Language :: Python :: 3.13
Classifier: Topic :: Software Development :: Libraries :: Python Modules
Classifier: Framework :: AsyncIO
Requires-Python: >=3.9
License-File: LICENSE
Requires-Dist: tenacity>=8.0.0
Requires-Dist: taskgroup>=0.0.0a4; python_version < "3.11"
Provides-Extra: dev
Requires-Dist: pytest>=7.0; extra == "dev"
Requires-Dist: pytest-asyncio>=0.21.0; extra == "dev"
Requires-Dist: mypy>=1.0; extra == "dev"
Requires-Dist: ruff>=0.1.0; extra == "dev"
Provides-Extra: docs
Requires-Dist: mkdocs>=1.5.0; extra == "docs"
Requires-Dist: mkdocs-material>=9.0.0; extra == "docs"
Requires-Dist: mkdocstrings[python]>=0.24.0; extra == "docs"
Requires-Dist: mkdocs-autorefs>=0.5.0; extra == "docs"
Dynamic: license-file
